{
  "id": "jf",
  "name": "Jumping Frog",
  "functions": {
    "add": {
      "id": "add",
      "name": "+",
      "core": true,
      "input": [
        {
          "id": "a",
          "name": "A",
          "type": "number"
        },
        {
          "id": "b",
          "name": "B",
          "type": "number"
        }
      ],
      "output": [
        {
          "id": "r",
          "name": "A + B",
          "type": "number"
        }
      ],
      "tokens": [],
      "wires": [],
      "values": {},
      "expandedParams": {}
    },
    "subtract": {
      "id": "subtract",
      "name": "-",
      "core": true,
      "input": [
        {
          "id": "suba",
          "name": "A",
          "type": "number"
        },
        {
          "id": "subb",
          "name": "B",
          "type": "number"
        }
      ],
      "output": [
        {
          "id": "subr",
          "name": "A - B",
          "type": "number"
        }
      ],
      "tokens": [],
      "wires": [],
      "values": {},
      "expandedParams": {}
    },
    "multiply": {
      "id": "multiply",
      "name": "×",
      "core": true,
      "input": [
        {
          "id": "am",
          "name": "A",
          "type": "number"
        },
        {
          "id": "bm",
          "name": "B",
          "type": "number"
        }
      ],
      "output": [
        {
          "id": "rm",
          "name": "A * B",
          "type": "number"
        }
      ],
      "tokens": [],
      "wires": [],
      "values": {},
      "expandedParams": {}
    },
    "divide": {
      "id": "divide",
      "name": "/",
      "core": true,
      "input": [
        {
          "id": "ad",
          "name": "A",
          "type": "number"
        },
        {
          "id": "bd",
          "name": "B",
          "type": "number"
        }
      ],
      "output": [
        {
          "id": "rd",
          "name": "A / B",
          "type": "number"
        }
      ],
      "tokens": [],
      "wires": [],
      "values": {},
      "expandedParams": {}
    },
    "greaterThan": {
      "id": "greaterThan",
      "name": ">",
      "core": true,
      "input": [
        {
          "id": "ga",
          "name": "A",
          "type": "number"
        },
        {
          "id": "gb",
          "name": "B",
          "type": "number"
        }
      ],
      "output": [
        {
          "id": "gr",
          "name": "A > B",
          "type": "boolean"
        }
      ],
      "tokens": [],
      "wires": [],
      "values": {},
      "expandedParams": {}
    },
    "lessThan": {
      "id": "lessThan",
      "name": "<",
      "core": true,
      "input": [
        {
          "id": "la",
          "name": "A",
          "type": "number"
        },
        {
          "id": "lb",
          "name": "B",
          "type": "number"
        }
      ],
      "output": [
        {
          "id": "lr",
          "name": "A < B",
          "type": "boolean"
        }
      ],
      "tokens": [],
      "wires": [],
      "values": {},
      "expandedParams": {}
    },
    "lessThanEql": {
      "id": "lessThanEql",
      "name": "<=",
      "core": true,
      "input": [
        {
          "id": "lessThanOrEqla",
          "name": "A",
          "type": "number"
        },
        {
          "id": "lessThanOrEqlb",
          "name": "B",
          "type": "number"
        }
      ],
      "output": [
        {
          "id": "lessThanOrEqlr",
          "name": "A <= B",
          "type": "boolean"
        }
      ],
      "tokens": [],
      "wires": [],
      "values": {},
      "expandedParams": {}
    },
    "greaterThanEql": {
      "id": "greaterThanEql",
      "name": ">=",
      "core": true,
      "input": [
        {
          "id": "greaterThanOrEqla",
          "name": "A",
          "type": "number"
        },
        {
          "id": "greaterThanOrEqlb",
          "name": "B",
          "type": "number"
        }
      ],
      "output": [
        {
          "id": "greaterThanOrEqlr",
          "name": "A >= B",
          "type": "boolean"
        }
      ],
      "tokens": [],
      "wires": [],
      "values": {},
      "expandedParams": {}
    },
    "equal": {
      "id": "equal",
      "name": "=",
      "core": true,
      "input": [
        {
          "id": "ea",
          "name": "A",
          "type": "through"
        },
        {
          "id": "eb",
          "name": "B",
          "type": "through"
        }
      ],
      "output": [
        {
          "id": "er",
          "name": "A = B",
          "type": "boolean"
        }
      ],
      "tokens": [],
      "wires": [],
      "values": {},
      "expandedParams": {}
    },
    "not": {
      "id": "not",
      "name": "NOT",
      "core": true,
      "input": [
        {
          "id": "notA",
          "name": "A",
          "type": "boolean"
        }
      ],
      "output": [
        {
          "id": "notR",
          "name": "not A",
          "type": "boolean"
        }
      ],
      "tokens": [],
      "wires": [],
      "values": {},
      "expandedParams": {}
    },
    "and": {
      "id": "and",
      "name": "AND",
      "core": true,
      "input": [
        {
          "id": "aa",
          "name": "A",
          "type": "boolean"
        },
        {
          "id": "ab",
          "name": "B",
          "type": "boolean"
        }
      ],
      "output": [
        {
          "id": "ar",
          "name": "A AND B",
          "type": "boolean"
        }
      ],
      "tokens": [],
      "wires": [],
      "values": {},
      "expandedParams": {}
    },
    "or": {
      "id": "or",
      "name": "OR",
      "core": true,
      "input": [
        {
          "id": "oa",
          "name": "A",
          "type": "boolean"
        },
        {
          "id": "ob",
          "name": "B",
          "type": "boolean"
        }
      ],
      "output": [
        {
          "id": "or",
          "name": "A OR B",
          "type": "boolean"
        }
      ],
      "tokens": [],
      "wires": [],
      "values": {},
      "expandedParams": {}
    },
    "select": {
      "id": "select",
      "name": "select",
      "core": true,
      "input": [
        {
          "id": "select1",
          "name": "switch",
          "type": "boolean"
        },
        {
          "id": "select2",
          "name": "true",
          "type": "through"
        },
        {
          "id": "select3",
          "name": "false",
          "type": "through"
        }
      ],
      "output": [
        {
          "id": "selectOut",
          "name": "data",
          "type": "through"
        }
      ],
      "tokens": [],
      "wires": [],
      "values": {},
      "expandedParams": {},
      "defaultSelectedType": "number"
    },
    "clamp": {
      "id": "clamp",
      "name": "clamp",
      "core": true,
      "input": [
        {
          "id": "clampValue",
          "name": "value",
          "type": "number"
        },
        {
          "id": "clampMin",
          "name": "min",
          "type": "number"
        },
        {
          "id": "clampMax",
          "name": "max",
          "type": "number"
        }
      ],
      "output": [
        {
          "id": "clampedValue",
          "name": "value",
          "type": "number"
        }
      ],
      "tokens": [],
      "wires": [],
      "values": {},
      "expandedParams": {}
    },
    "isKeyDown": {
      "id": "isKeyDown",
      "name": "isKeyDown",
      "core": true,
      "input": [
        {
          "id": "isKeyDownInput",
          "name": "input",
          "type": "input"
        },
        {
          "id": "isKeyDownValue",
          "name": "keyName",
          "type": "string"
        }
      ],
      "output": [
        {
          "id": "isKeyDownOut",
          "name": "value",
          "type": "boolean"
        }
      ],
      "tokens": [],
      "wires": [],
      "values": {},
      "expandedParams": {}
    },
    "draw": {
      "id": "draw",
      "name": "draw rectangle",
      "core": true,
      "input": [
        {
          "id": "drawScene",
          "name": "scene",
          "type": "scene"
        },
        {
          "id": "drawShape",
          "name": "shape",
          "type": "rect"
        }
      ],
      "output": [
        {
          "id": "drawSceneOut",
          "name": "scene",
          "type": "scene"
        }
      ],
      "tokens": [],
      "wires": [],
      "values": {},
      "expandedParams": {}
    },
    "drawText": {
      "id": "drawText",
      "name": "draw text",
      "core": true,
      "input": [
        {
          "id": "drawTextScene",
          "name": "scene",
          "type": "scene"
        },
        {
          "id": "drawText",
          "name": "text",
          "type": "text"
        }
      ],
      "output": [
        {
          "id": "drawTextOut",
          "name": "scene",
          "type": "scene"
        }
      ],
      "tokens": [],
      "wires": [],
      "values": {},
      "expandedParams": {}
    },
    "drawImage": {
      "id": "drawImage",
      "name": "draw image",
      "core": true,
      "input": [
        {
          "id": "drawImageScene",
          "name": "scene",
          "type": "scene"
        },
        {
          "id": "drawImageImage",
          "name": "image",
          "type": "image"
        }
      ],
      "output": [
        {
          "id": "drawImageOut",
          "name": "scene",
          "type": "scene"
        }
      ],
      "tokens": [],
      "wires": [],
      "values": {},
      "expandedParams": {}
    },
    "urkjxr6zsnsiz9yizq7x8": {
      "id": "urkjxr6zsnsiz9yizq7x8",
      "name": "main",
      "core": false,
      "input": [
        {
          "id": "state",
          "name": "state",
          "type": "state"
        },
        {
          "id": "input",
          "name": "input",
          "type": "input"
        }
      ],
      "output": [
        {
          "id": "k8xtm619qq9jqzk7wb0a9q",
          "name": "state",
          "type": "state"
        },
        {
          "id": "pfshij23yhqr5uy3l952",
          "name": "scene",
          "type": "scene"
        }
      ],
      "tokens": [
        {
          "id": "kwpm9bskske1ixbfbh2sc",
          "position": {
            "x": 325,
            "y": 6
          },
          "fn": "juj4lyvbfrqqpidozu71m",
          "values": {},
          "expandedParams": {}
        },
        {
          "id": "qw0subbo0z4mkg9vfd51s",
          "position": {
            "x": 708,
            "y": 100
          },
          "fn": "jm3lc1slldwo6k7vuuu5",
          "values": {},
          "expandedParams": {}
        }
      ],
      "wires": [
        {
          "id": "kwpm9bskske1ixbfbh2sc.dzxeucqcofplf8r3z5df8",
          "from": {
            "target": "urkjxr6zsnsiz9yizq7x8",
            "param": "state",
            "path": "urkjxr6zsnsiz9yizq7x8.state"
          },
          "to": {
            "target": "kwpm9bskske1ixbfbh2sc",
            "param": "dzxeucqcofplf8r3z5df8",
            "path": "kwpm9bskske1ixbfbh2sc.dzxeucqcofplf8r3z5df8"
          }
        },
        {
          "id": "kwpm9bskske1ixbfbh2sc.r5k4xxambvie9dfq3r18",
          "from": {
            "target": "urkjxr6zsnsiz9yizq7x8",
            "param": "input",
            "path": "urkjxr6zsnsiz9yizq7x8.input"
          },
          "to": {
            "target": "kwpm9bskske1ixbfbh2sc",
            "param": "r5k4xxambvie9dfq3r18",
            "path": "kwpm9bskske1ixbfbh2sc.r5k4xxambvie9dfq3r18"
          }
        },
        {
          "id": "urkjxr6zsnsiz9yizq7x8.k8xtm619qq9jqzk7wb0a9q",
          "from": {
            "target": "kwpm9bskske1ixbfbh2sc",
            "param": "6p0dkr4icqdoqfzzn1ci7f",
            "path": "kwpm9bskske1ixbfbh2sc.6p0dkr4icqdoqfzzn1ci7f"
          },
          "to": {
            "target": "urkjxr6zsnsiz9yizq7x8",
            "param": "k8xtm619qq9jqzk7wb0a9q",
            "path": "urkjxr6zsnsiz9yizq7x8.k8xtm619qq9jqzk7wb0a9q"
          }
        },
        {
          "id": "qw0subbo0z4mkg9vfd51s.06chbzwndnnv7ej79h111d3",
          "from": {
            "target": "kwpm9bskske1ixbfbh2sc",
            "param": "6p0dkr4icqdoqfzzn1ci7f",
            "path": "kwpm9bskske1ixbfbh2sc.6p0dkr4icqdoqfzzn1ci7f"
          },
          "to": {
            "target": "qw0subbo0z4mkg9vfd51s",
            "param": "06chbzwndnnv7ej79h111d3",
            "path": "qw0subbo0z4mkg9vfd51s.06chbzwndnnv7ej79h111d3"
          }
        },
        {
          "id": "urkjxr6zsnsiz9yizq7x8.pfshij23yhqr5uy3l952",
          "from": {
            "target": "qw0subbo0z4mkg9vfd51s",
            "param": "gy6jkwawe3et4wiwx2cj0e",
            "path": "qw0subbo0z4mkg9vfd51s.gy6jkwawe3et4wiwx2cj0e"
          },
          "to": {
            "target": "urkjxr6zsnsiz9yizq7x8",
            "param": "pfshij23yhqr5uy3l952",
            "path": "urkjxr6zsnsiz9yizq7x8.pfshij23yhqr5uy3l952"
          }
        }
      ],
      "values": {},
      "expandedParams": {}
    },
    "juj4lyvbfrqqpidozu71m": {
      "id": "juj4lyvbfrqqpidozu71m",
      "name": "update",
      "core": false,
      "input": [
        {
          "id": "dzxeucqcofplf8r3z5df8",
          "name": "state",
          "type": "state"
        },
        {
          "id": "r5k4xxambvie9dfq3r18",
          "name": "input",
          "type": "input"
        }
      ],
      "output": [
        {
          "id": "6p0dkr4icqdoqfzzn1ci7f",
          "name": "state",
          "type": "state"
        }
      ],
      "tokens": [
        {
          "id": "an9p39kforbug0ps9wlh7",
          "position": {
            "x": 1067,
            "y": -5
          },
          "fn": "shsuv6wj1x8s1wnj8gvax",
          "values": {},
          "expandedParams": {}
        },
        {
          "id": "9c8u3wmu5znhblrhwnec",
          "position": {
            "x": 847,
            "y": -9
          },
          "fn": "0lzr4h2m7hwaxd4r63zun7",
          "values": {},
          "expandedParams": {}
        },
        {
          "id": "bj3xdd4auallu06vfq2w2",
          "position": {
            "x": 304,
            "y": -81
          },
          "fn": "vfvl50tn3vhgohtfdbnzev",
          "values": {},
          "expandedParams": {}
        },
        {
          "id": "jog3d8ko0ga94657yuy11m",
          "position": {
            "x": 593,
            "y": 5
          },
          "fn": "tmmlz7una1bbx6pvgacr9g",
          "values": {},
          "expandedParams": {}
        }
      ],
      "wires": [
        {
          "id": "juj4lyvbfrqqpidozu71m.6p0dkr4icqdoqfzzn1ci7f",
          "from": {
            "target": "an9p39kforbug0ps9wlh7",
            "param": "ogo5wmnmnipb9yppkg9c4k",
            "path": "an9p39kforbug0ps9wlh7.ogo5wmnmnipb9yppkg9c4k"
          },
          "to": {
            "target": "juj4lyvbfrqqpidozu71m",
            "param": "6p0dkr4icqdoqfzzn1ci7f",
            "path": "juj4lyvbfrqqpidozu71m.6p0dkr4icqdoqfzzn1ci7f"
          }
        },
        {
          "id": "an9p39kforbug0ps9wlh7.u219ogee1pjhlhpt9s12kl",
          "from": {
            "target": "bj3xdd4auallu06vfq2w2",
            "param": "yh9cjlrtkl2rw0owwjtei",
            "path": "bj3xdd4auallu06vfq2w2.yh9cjlrtkl2rw0owwjtei"
          },
          "to": {
            "target": "jog3d8ko0ga94657yuy11m",
            "param": "1ehgwb1huoahv112xqi5mk",
            "path": "jog3d8ko0ga94657yuy11m.1ehgwb1huoahv112xqi5mk"
          }
        },
        {
          "id": "bj3xdd4auallu06vfq2w2.9ahhuo4j2i6q7td8dqael",
          "from": {
            "target": "juj4lyvbfrqqpidozu71m",
            "param": "r5k4xxambvie9dfq3r18",
            "path": "juj4lyvbfrqqpidozu71m.r5k4xxambvie9dfq3r18"
          },
          "to": {
            "target": "bj3xdd4auallu06vfq2w2",
            "param": "9ahhuo4j2i6q7td8dqael",
            "path": "bj3xdd4auallu06vfq2w2.9ahhuo4j2i6q7td8dqael"
          }
        },
        {
          "id": "an9p39kforbug0ps9wlh7.u219ogee1pjhlhpt9s12kl",
          "from": {
            "target": "jog3d8ko0ga94657yuy11m",
            "param": "zyr58ywgczoq3uduruanyq",
            "path": "jog3d8ko0ga94657yuy11m.zyr58ywgczoq3uduruanyq"
          },
          "to": {
            "target": "9c8u3wmu5znhblrhwnec",
            "param": "7ogjeotttbpc5csrzju0m",
            "path": "9c8u3wmu5znhblrhwnec.7ogjeotttbpc5csrzju0m"
          }
        },
        {
          "id": "jog3d8ko0ga94657yuy11m.nvwh33tneyo1osd92jwoet",
          "from": {
            "target": "juj4lyvbfrqqpidozu71m",
            "param": "r5k4xxambvie9dfq3r18",
            "path": "juj4lyvbfrqqpidozu71m.r5k4xxambvie9dfq3r18"
          },
          "to": {
            "target": "jog3d8ko0ga94657yuy11m",
            "param": "nvwh33tneyo1osd92jwoet",
            "path": "jog3d8ko0ga94657yuy11m.nvwh33tneyo1osd92jwoet"
          }
        },
        {
          "id": "an9p39kforbug0ps9wlh7.u219ogee1pjhlhpt9s12kl",
          "from": {
            "target": "9c8u3wmu5znhblrhwnec",
            "param": "q0zhgqw4179d2j614syjo",
            "path": "9c8u3wmu5znhblrhwnec.q0zhgqw4179d2j614syjo"
          },
          "to": {
            "target": "an9p39kforbug0ps9wlh7",
            "param": "u219ogee1pjhlhpt9s12kl",
            "path": "an9p39kforbug0ps9wlh7.u219ogee1pjhlhpt9s12kl"
          }
        },
        {
          "id": "bj3xdd4auallu06vfq2w2.pwag5mprqgbi9nfq7ukym",
          "from": {
            "target": "juj4lyvbfrqqpidozu71m",
            "param": "dzxeucqcofplf8r3z5df8",
            "path": "juj4lyvbfrqqpidozu71m.dzxeucqcofplf8r3z5df8"
          },
          "to": {
            "target": "bj3xdd4auallu06vfq2w2",
            "param": "pwag5mprqgbi9nfq7ukym",
            "path": "bj3xdd4auallu06vfq2w2.pwag5mprqgbi9nfq7ukym"
          }
        }
      ],
      "values": {},
      "expandedParams": {}
    },
    "jm3lc1slldwo6k7vuuu5": {
      "id": "jm3lc1slldwo6k7vuuu5",
      "name": "view",
      "core": false,
      "input": [
        {
          "id": "06chbzwndnnv7ej79h111d3",
          "name": "state",
          "type": "state"
        }
      ],
      "output": [
        {
          "id": "gy6jkwawe3et4wiwx2cj0e",
          "name": "scene",
          "type": "scene"
        }
      ],
      "tokens": [
        {
          "id": "ekh8yskn9pk72h2kjv5p5b",
          "position": {
            "x": 587,
            "y": 35
          },
          "fn": "drawImage",
          "values": {
            "ekh8yskn9pk72h2kjv5p5b.drawImageImage.height": 100,
            "ekh8yskn9pk72h2kjv5p5b.drawImageImage.width": 100,
            "ekh8yskn9pk72h2kjv5p5b.drawImageImage.imageSrc": "/sprites/frog.png"
          },
          "expandedParams": {
            "ekh8yskn9pk72h2kjv5p5b.drawImageImage": true
          }
        }
      ],
      "wires": [
        {
          "id": "ekh8yskn9pk72h2kjv5p5b.drawImageImage.x",
          "from": {
            "target": "jm3lc1slldwo6k7vuuu5",
            "param": "s9c1c1nbkeazla8wmx9fn",
            "path": "jm3lc1slldwo6k7vuuu5.06chbzwndnnv7ej79h111d3.s9c1c1nbkeazla8wmx9fn"
          },
          "to": {
            "target": "ekh8yskn9pk72h2kjv5p5b",
            "param": "x",
            "path": "ekh8yskn9pk72h2kjv5p5b.drawImageImage.x"
          }
        },
        {
          "id": "ekh8yskn9pk72h2kjv5p5b.drawImageImage.y",
          "from": {
            "target": "jm3lc1slldwo6k7vuuu5",
            "param": "zajbxwkqcjvnt1gunxntl",
            "path": "jm3lc1slldwo6k7vuuu5.06chbzwndnnv7ej79h111d3.zajbxwkqcjvnt1gunxntl"
          },
          "to": {
            "target": "ekh8yskn9pk72h2kjv5p5b",
            "param": "y",
            "path": "ekh8yskn9pk72h2kjv5p5b.drawImageImage.y"
          }
        },
        {
          "id": "jm3lc1slldwo6k7vuuu5.gy6jkwawe3et4wiwx2cj0e",
          "from": {
            "target": "ekh8yskn9pk72h2kjv5p5b",
            "param": "drawImageOut",
            "path": "ekh8yskn9pk72h2kjv5p5b.drawImageOut"
          },
          "to": {
            "target": "jm3lc1slldwo6k7vuuu5",
            "param": "gy6jkwawe3et4wiwx2cj0e",
            "path": "jm3lc1slldwo6k7vuuu5.gy6jkwawe3et4wiwx2cj0e"
          }
        }
      ],
      "values": {},
      "expandedParams": {
        "jm3lc1slldwo6k7vuuu5.06chbzwndnnv7ej79h111d3": true
      }
    },
    "shsuv6wj1x8s1wnj8gvax": {
      "id": "shsuv6wj1x8s1wnj8gvax",
      "name": "restictArea",
      "core": false,
      "input": [
        {
          "id": "u219ogee1pjhlhpt9s12kl",
          "name": "state",
          "type": "state"
        }
      ],
      "output": [
        {
          "id": "ogo5wmnmnipb9yppkg9c4k",
          "name": "state",
          "type": "state"
        }
      ],
      "tokens": [
        {
          "id": "wztz5knlveko9dh1i9jy3",
          "position": {
            "x": 582,
            "y": 10
          },
          "fn": "clamp",
          "values": {
            "wztz5knlveko9dh1i9jy3.clampMin": 0,
            "wztz5knlveko9dh1i9jy3.clampMax": 700
          },
          "expandedParams": {}
        },
        {
          "id": "jhml8xbi4e106hgppknik",
          "position": {
            "x": 568,
            "y": 147
          },
          "fn": "clamp",
          "values": {
            "jhml8xbi4e106hgppknik.clampMin": 0,
            "jhml8xbi4e106hgppknik.clampMax": 500
          },
          "expandedParams": {}
        }
      ],
      "wires": [
        {
          "id": "wztz5knlveko9dh1i9jy3.clampValue",
          "from": {
            "target": "shsuv6wj1x8s1wnj8gvax",
            "param": "s9c1c1nbkeazla8wmx9fn",
            "path": "shsuv6wj1x8s1wnj8gvax.u219ogee1pjhlhpt9s12kl.s9c1c1nbkeazla8wmx9fn"
          },
          "to": {
            "target": "wztz5knlveko9dh1i9jy3",
            "param": "clampValue",
            "path": "wztz5knlveko9dh1i9jy3.clampValue"
          }
        },
        {
          "id": "shsuv6wj1x8s1wnj8gvax.ogo5wmnmnipb9yppkg9c4k.s9c1c1nbkeazla8wmx9fn",
          "from": {
            "target": "wztz5knlveko9dh1i9jy3",
            "param": "clampedValue",
            "path": "wztz5knlveko9dh1i9jy3.clampedValue"
          },
          "to": {
            "target": "shsuv6wj1x8s1wnj8gvax",
            "param": "s9c1c1nbkeazla8wmx9fn",
            "path": "shsuv6wj1x8s1wnj8gvax.ogo5wmnmnipb9yppkg9c4k.s9c1c1nbkeazla8wmx9fn"
          }
        },
        {
          "id": "jhml8xbi4e106hgppknik.clampValue",
          "from": {
            "target": "shsuv6wj1x8s1wnj8gvax",
            "param": "zajbxwkqcjvnt1gunxntl",
            "path": "shsuv6wj1x8s1wnj8gvax.u219ogee1pjhlhpt9s12kl.zajbxwkqcjvnt1gunxntl"
          },
          "to": {
            "target": "jhml8xbi4e106hgppknik",
            "param": "clampValue",
            "path": "jhml8xbi4e106hgppknik.clampValue"
          }
        },
        {
          "id": "shsuv6wj1x8s1wnj8gvax.ogo5wmnmnipb9yppkg9c4k.zajbxwkqcjvnt1gunxntl",
          "from": {
            "target": "jhml8xbi4e106hgppknik",
            "param": "clampedValue",
            "path": "jhml8xbi4e106hgppknik.clampedValue"
          },
          "to": {
            "target": "shsuv6wj1x8s1wnj8gvax",
            "param": "zajbxwkqcjvnt1gunxntl",
            "path": "shsuv6wj1x8s1wnj8gvax.ogo5wmnmnipb9yppkg9c4k.zajbxwkqcjvnt1gunxntl"
          }
        },
        {
          "id": "shsuv6wj1x8s1wnj8gvax.ogo5wmnmnipb9yppkg9c4k",
          "from": {
            "target": "shsuv6wj1x8s1wnj8gvax",
            "param": "u219ogee1pjhlhpt9s12kl",
            "path": "shsuv6wj1x8s1wnj8gvax.u219ogee1pjhlhpt9s12kl"
          },
          "to": {
            "target": "shsuv6wj1x8s1wnj8gvax",
            "param": "ogo5wmnmnipb9yppkg9c4k",
            "path": "shsuv6wj1x8s1wnj8gvax.ogo5wmnmnipb9yppkg9c4k"
          }
        }
      ],
      "values": {},
      "expandedParams": {
        "shsuv6wj1x8s1wnj8gvax.u219ogee1pjhlhpt9s12kl": true,
        "shsuv6wj1x8s1wnj8gvax.ogo5wmnmnipb9yppkg9c4k": true
      }
    },
    "0lzr4h2m7hwaxd4r63zun7": {
      "id": "0lzr4h2m7hwaxd4r63zun7",
      "name": "gravity",
      "core": false,
      "input": [
        {
          "id": "7ogjeotttbpc5csrzju0m",
          "name": "state",
          "type": "state"
        }
      ],
      "output": [
        {
          "id": "q0zhgqw4179d2j614syjo",
          "name": "state",
          "type": "state"
        }
      ],
      "tokens": [
        {
          "id": "fvw7uzwg7mqqtg3xx5avfn",
          "position": {
            "x": 941,
            "y": 138
          },
          "fn": "select",
          "values": {
            "fvw7uzwg7mqqtg3xx5avfn.select3": 0
          },
          "expandedParams": {}
        },
        {
          "id": "egs6btpdmk4vnyk3a2r1a",
          "position": {
            "x": 261,
            "y": -22
          },
          "fn": "add",
          "values": {},
          "expandedParams": {}
        },
        {
          "id": "gpul4dhbjfqs54dz794jlr",
          "position": {
            "x": 259,
            "y": 108
          },
          "fn": "add",
          "values": {
            "gpul4dhbjfqs54dz794jlr.b": 2
          },
          "expandedParams": {}
        },
        {
          "id": "3xlkwp5423p0ptvsoq3jzbc",
          "position": {
            "x": 624,
            "y": 51
          },
          "fn": "zdgq1qsxgh5f9dpdmv7a",
          "values": {},
          "expandedParams": {}
        }
      ],
      "wires": [
        {
          "id": "0lzr4h2m7hwaxd4r63zun7.q0zhgqw4179d2j614syjo",
          "from": {
            "target": "0lzr4h2m7hwaxd4r63zun7",
            "param": "7ogjeotttbpc5csrzju0m",
            "path": "0lzr4h2m7hwaxd4r63zun7.7ogjeotttbpc5csrzju0m"
          },
          "to": {
            "target": "0lzr4h2m7hwaxd4r63zun7",
            "param": "q0zhgqw4179d2j614syjo",
            "path": "0lzr4h2m7hwaxd4r63zun7.q0zhgqw4179d2j614syjo"
          }
        },
        {
          "id": "egs6btpdmk4vnyk3a2r1a.a",
          "from": {
            "target": "0lzr4h2m7hwaxd4r63zun7",
            "param": "zajbxwkqcjvnt1gunxntl",
            "path": "0lzr4h2m7hwaxd4r63zun7.7ogjeotttbpc5csrzju0m.zajbxwkqcjvnt1gunxntl"
          },
          "to": {
            "target": "egs6btpdmk4vnyk3a2r1a",
            "param": "a",
            "path": "egs6btpdmk4vnyk3a2r1a.a"
          }
        },
        {
          "id": "0lzr4h2m7hwaxd4r63zun7.q0zhgqw4179d2j614syjo.zajbxwkqcjvnt1gunxntl",
          "from": {
            "target": "egs6btpdmk4vnyk3a2r1a",
            "param": "r",
            "path": "egs6btpdmk4vnyk3a2r1a.r"
          },
          "to": {
            "target": "3xlkwp5423p0ptvsoq3jzbc",
            "param": "pmofpdfv0a88ye7qhgc2f",
            "path": "3xlkwp5423p0ptvsoq3jzbc.pmofpdfv0a88ye7qhgc2f"
          }
        },
        {
          "id": "0lzr4h2m7hwaxd4r63zun7.q0zhgqw4179d2j614syjo.9mclho2pkelwm1p64zm5t",
          "from": {
            "target": "fvw7uzwg7mqqtg3xx5avfn",
            "param": "selectOut",
            "path": "fvw7uzwg7mqqtg3xx5avfn.selectOut"
          },
          "to": {
            "target": "0lzr4h2m7hwaxd4r63zun7",
            "param": "9mclho2pkelwm1p64zm5t",
            "path": "0lzr4h2m7hwaxd4r63zun7.q0zhgqw4179d2j614syjo.9mclho2pkelwm1p64zm5t"
          }
        },
        {
          "id": "gpul4dhbjfqs54dz794jlr.a",
          "from": {
            "target": "0lzr4h2m7hwaxd4r63zun7",
            "param": "9mclho2pkelwm1p64zm5t",
            "path": "0lzr4h2m7hwaxd4r63zun7.7ogjeotttbpc5csrzju0m.9mclho2pkelwm1p64zm5t"
          },
          "to": {
            "target": "gpul4dhbjfqs54dz794jlr",
            "param": "a",
            "path": "gpul4dhbjfqs54dz794jlr.a"
          }
        },
        {
          "id": "fvw7uzwg7mqqtg3xx5avfn.select1",
          "from": {
            "target": "3xlkwp5423p0ptvsoq3jzbc",
            "param": "vb5yqy3isbba2ld8gjb5na",
            "path": "3xlkwp5423p0ptvsoq3jzbc.vb5yqy3isbba2ld8gjb5na"
          },
          "to": {
            "target": "fvw7uzwg7mqqtg3xx5avfn",
            "param": "select1",
            "path": "fvw7uzwg7mqqtg3xx5avfn.select1"
          }
        },
        {
          "id": "fvw7uzwg7mqqtg3xx5avfn.select2",
          "from": {
            "target": "gpul4dhbjfqs54dz794jlr",
            "param": "r",
            "path": "gpul4dhbjfqs54dz794jlr.r"
          },
          "to": {
            "target": "fvw7uzwg7mqqtg3xx5avfn",
            "param": "select2",
            "path": "fvw7uzwg7mqqtg3xx5avfn.select2"
          }
        },
        {
          "id": "egs6btpdmk4vnyk3a2r1a.b",
          "from": {
            "target": "0lzr4h2m7hwaxd4r63zun7",
            "param": "9mclho2pkelwm1p64zm5t",
            "path": "0lzr4h2m7hwaxd4r63zun7.7ogjeotttbpc5csrzju0m.9mclho2pkelwm1p64zm5t"
          },
          "to": {
            "target": "egs6btpdmk4vnyk3a2r1a",
            "param": "b",
            "path": "egs6btpdmk4vnyk3a2r1a.b"
          }
        },
        {
          "id": "0lzr4h2m7hwaxd4r63zun7.q0zhgqw4179d2j614syjo.zajbxwkqcjvnt1gunxntl",
          "from": {
            "target": "egs6btpdmk4vnyk3a2r1a",
            "param": "r",
            "path": "egs6btpdmk4vnyk3a2r1a.r"
          },
          "to": {
            "target": "0lzr4h2m7hwaxd4r63zun7",
            "param": "zajbxwkqcjvnt1gunxntl",
            "path": "0lzr4h2m7hwaxd4r63zun7.q0zhgqw4179d2j614syjo.zajbxwkqcjvnt1gunxntl"
          }
        }
      ],
      "values": {},
      "expandedParams": {
        "0lzr4h2m7hwaxd4r63zun7.7ogjeotttbpc5csrzju0m": true,
        "0lzr4h2m7hwaxd4r63zun7.q0zhgqw4179d2j614syjo": true
      }
    },
    "4cfqgdzfba8mvysx2tf11q": {
      "id": "4cfqgdzfba8mvysx2tf11q",
      "name": "horizonalMove",
      "core": false,
      "input": [],
      "output": [],
      "tokens": [],
      "wires": [],
      "values": {},
      "expandedParams": {}
    },
    "vfvl50tn3vhgohtfdbnzev": {
      "id": "vfvl50tn3vhgohtfdbnzev",
      "name": "horizontalMove",
      "core": false,
      "input": [
        {
          "id": "pwag5mprqgbi9nfq7ukym",
          "name": "state",
          "type": "state"
        },
        {
          "id": "9ahhuo4j2i6q7td8dqael",
          "name": "input",
          "type": "input"
        }
      ],
      "output": [
        {
          "id": "yh9cjlrtkl2rw0owwjtei",
          "name": "state",
          "type": "state"
        }
      ],
      "tokens": [
        {
          "id": "bhkown4yea90m937d04ff1i",
          "position": {
            "x": 298,
            "y": 149
          },
          "fn": "isKeyDown",
          "values": {
            "bhkown4yea90m937d04ff1i.isKeyDownValue": "ArrowLeft"
          },
          "expandedParams": {}
        },
        {
          "id": "w1jjwq16ycprjuc8e4f7s",
          "position": {
            "x": 922,
            "y": 20
          },
          "fn": "add",
          "values": {},
          "expandedParams": {}
        },
        {
          "id": "nm68tu6jaiem978qfbu4lg",
          "position": {
            "x": 644,
            "y": 137
          },
          "fn": "select",
          "values": {
            "nm68tu6jaiem978qfbu4lg.select2": -20,
            "nm68tu6jaiem978qfbu4lg.select3": 0
          },
          "expandedParams": {}
        },
        {
          "id": "hgpm1ypy5bqz1ey46w9u5b",
          "position": {
            "x": 559,
            "y": -171
          },
          "fn": "isKeyDown",
          "values": {
            "hgpm1ypy5bqz1ey46w9u5b.isKeyDownValue": "ArrowRight"
          },
          "expandedParams": {}
        },
        {
          "id": "tx49io2jm2d8qgjpkt86",
          "position": {
            "x": 1124,
            "y": -52
          },
          "fn": "add",
          "values": {},
          "expandedParams": {}
        },
        {
          "id": "dcsqrg20piuaxedw8dtd",
          "position": {
            "x": 854,
            "y": -161
          },
          "fn": "select",
          "values": {
            "dcsqrg20piuaxedw8dtd.select2": 20,
            "dcsqrg20piuaxedw8dtd.select3": 0
          },
          "expandedParams": {}
        }
      ],
      "wires": [
        {
          "id": "vfvl50tn3vhgohtfdbnzev.yh9cjlrtkl2rw0owwjtei",
          "from": {
            "target": "vfvl50tn3vhgohtfdbnzev",
            "param": "pwag5mprqgbi9nfq7ukym",
            "path": "vfvl50tn3vhgohtfdbnzev.pwag5mprqgbi9nfq7ukym"
          },
          "to": {
            "target": "vfvl50tn3vhgohtfdbnzev",
            "param": "yh9cjlrtkl2rw0owwjtei",
            "path": "vfvl50tn3vhgohtfdbnzev.yh9cjlrtkl2rw0owwjtei"
          }
        },
        {
          "id": "bhkown4yea90m937d04ff1i.isKeyDownInput",
          "from": {
            "target": "vfvl50tn3vhgohtfdbnzev",
            "param": "9ahhuo4j2i6q7td8dqael",
            "path": "vfvl50tn3vhgohtfdbnzev.9ahhuo4j2i6q7td8dqael"
          },
          "to": {
            "target": "bhkown4yea90m937d04ff1i",
            "param": "isKeyDownInput",
            "path": "bhkown4yea90m937d04ff1i.isKeyDownInput"
          }
        },
        {
          "id": "w1jjwq16ycprjuc8e4f7s.a",
          "from": {
            "target": "vfvl50tn3vhgohtfdbnzev",
            "param": "s9c1c1nbkeazla8wmx9fn",
            "path": "vfvl50tn3vhgohtfdbnzev.pwag5mprqgbi9nfq7ukym.s9c1c1nbkeazla8wmx9fn"
          },
          "to": {
            "target": "w1jjwq16ycprjuc8e4f7s",
            "param": "a",
            "path": "w1jjwq16ycprjuc8e4f7s.a"
          }
        },
        {
          "id": "nm68tu6jaiem978qfbu4lg.select1",
          "from": {
            "target": "bhkown4yea90m937d04ff1i",
            "param": "isKeyDownOut",
            "path": "bhkown4yea90m937d04ff1i.isKeyDownOut"
          },
          "to": {
            "target": "nm68tu6jaiem978qfbu4lg",
            "param": "select1",
            "path": "nm68tu6jaiem978qfbu4lg.select1"
          }
        },
        {
          "id": "w1jjwq16ycprjuc8e4f7s.b",
          "from": {
            "target": "nm68tu6jaiem978qfbu4lg",
            "param": "selectOut",
            "path": "nm68tu6jaiem978qfbu4lg.selectOut"
          },
          "to": {
            "target": "w1jjwq16ycprjuc8e4f7s",
            "param": "b",
            "path": "w1jjwq16ycprjuc8e4f7s.b"
          }
        },
        {
          "id": "vfvl50tn3vhgohtfdbnzev.yh9cjlrtkl2rw0owwjtei.s9c1c1nbkeazla8wmx9fn",
          "from": {
            "target": "w1jjwq16ycprjuc8e4f7s",
            "param": "r",
            "path": "w1jjwq16ycprjuc8e4f7s.r"
          },
          "to": {
            "target": "tx49io2jm2d8qgjpkt86",
            "param": "b",
            "path": "tx49io2jm2d8qgjpkt86.b"
          }
        },
        {
          "id": "hgpm1ypy5bqz1ey46w9u5b.isKeyDownInput",
          "from": {
            "target": "vfvl50tn3vhgohtfdbnzev",
            "param": "9ahhuo4j2i6q7td8dqael",
            "path": "vfvl50tn3vhgohtfdbnzev.9ahhuo4j2i6q7td8dqael"
          },
          "to": {
            "target": "hgpm1ypy5bqz1ey46w9u5b",
            "param": "isKeyDownInput",
            "path": "hgpm1ypy5bqz1ey46w9u5b.isKeyDownInput"
          }
        },
        {
          "id": "dcsqrg20piuaxedw8dtd.select1",
          "from": {
            "target": "hgpm1ypy5bqz1ey46w9u5b",
            "param": "isKeyDownOut",
            "path": "hgpm1ypy5bqz1ey46w9u5b.isKeyDownOut"
          },
          "to": {
            "target": "dcsqrg20piuaxedw8dtd",
            "param": "select1",
            "path": "dcsqrg20piuaxedw8dtd.select1"
          }
        },
        {
          "id": "tx49io2jm2d8qgjpkt86.a",
          "from": {
            "target": "dcsqrg20piuaxedw8dtd",
            "param": "selectOut",
            "path": "dcsqrg20piuaxedw8dtd.selectOut"
          },
          "to": {
            "target": "tx49io2jm2d8qgjpkt86",
            "param": "a",
            "path": "tx49io2jm2d8qgjpkt86.a"
          }
        },
        {
          "id": "vfvl50tn3vhgohtfdbnzev.yh9cjlrtkl2rw0owwjtei.s9c1c1nbkeazla8wmx9fn",
          "from": {
            "target": "tx49io2jm2d8qgjpkt86",
            "param": "r",
            "path": "tx49io2jm2d8qgjpkt86.r"
          },
          "to": {
            "target": "vfvl50tn3vhgohtfdbnzev",
            "param": "s9c1c1nbkeazla8wmx9fn",
            "path": "vfvl50tn3vhgohtfdbnzev.yh9cjlrtkl2rw0owwjtei.s9c1c1nbkeazla8wmx9fn"
          }
        }
      ],
      "values": {},
      "expandedParams": {
        "vfvl50tn3vhgohtfdbnzev.pwag5mprqgbi9nfq7ukym": true,
        "vfvl50tn3vhgohtfdbnzev.yh9cjlrtkl2rw0owwjtei": true
      }
    },
    "tmmlz7una1bbx6pvgacr9g": {
      "id": "tmmlz7una1bbx6pvgacr9g",
      "name": "jump",
      "core": false,
      "input": [
        {
          "id": "1ehgwb1huoahv112xqi5mk",
          "name": "state",
          "type": "state"
        },
        {
          "id": "nvwh33tneyo1osd92jwoet",
          "name": "input",
          "type": "input"
        }
      ],
      "output": [
        {
          "id": "zyr58ywgczoq3uduruanyq",
          "name": "state",
          "type": "state"
        }
      ],
      "tokens": [
        {
          "id": "84wrbsrf22qanhqadwe978",
          "position": {
            "x": 204,
            "y": 199
          },
          "fn": "isKeyDown",
          "values": {
            "84wrbsrf22qanhqadwe978.isKeyDownValue": "ArrowUp"
          },
          "expandedParams": {}
        },
        {
          "id": "qf1hpzmnbhap3g58xo263b",
          "position": {
            "x": 984,
            "y": 2
          },
          "fn": "select",
          "values": {
            "qf1hpzmnbhap3g58xo263b.select2": -30
          },
          "expandedParams": {}
        },
        {
          "id": "obi41bninohy4snvlz1m7",
          "position": {
            "x": 209,
            "y": 72
          },
          "fn": "zdgq1qsxgh5f9dpdmv7a",
          "values": {},
          "expandedParams": {}
        },
        {
          "id": "2awtp9lbdy66c670s25zo",
          "position": {
            "x": 718,
            "y": 124
          },
          "fn": "and",
          "values": {},
          "expandedParams": {}
        },
        {
          "id": "n3mr51aig4mkncyt8lpbg",
          "position": {
            "x": 461,
            "y": 97
          },
          "fn": "not",
          "values": {},
          "expandedParams": {}
        }
      ],
      "wires": [
        {
          "id": "tmmlz7una1bbx6pvgacr9g.zyr58ywgczoq3uduruanyq",
          "from": {
            "target": "tmmlz7una1bbx6pvgacr9g",
            "param": "1ehgwb1huoahv112xqi5mk",
            "path": "tmmlz7una1bbx6pvgacr9g.1ehgwb1huoahv112xqi5mk"
          },
          "to": {
            "target": "tmmlz7una1bbx6pvgacr9g",
            "param": "zyr58ywgczoq3uduruanyq",
            "path": "tmmlz7una1bbx6pvgacr9g.zyr58ywgczoq3uduruanyq"
          }
        },
        {
          "id": "84wrbsrf22qanhqadwe978.isKeyDownInput",
          "from": {
            "target": "tmmlz7una1bbx6pvgacr9g",
            "param": "nvwh33tneyo1osd92jwoet",
            "path": "tmmlz7una1bbx6pvgacr9g.nvwh33tneyo1osd92jwoet"
          },
          "to": {
            "target": "84wrbsrf22qanhqadwe978",
            "param": "isKeyDownInput",
            "path": "84wrbsrf22qanhqadwe978.isKeyDownInput"
          }
        },
        {
          "id": "obi41bninohy4snvlz1m7.pmofpdfv0a88ye7qhgc2f",
          "from": {
            "target": "tmmlz7una1bbx6pvgacr9g",
            "param": "zajbxwkqcjvnt1gunxntl",
            "path": "tmmlz7una1bbx6pvgacr9g.1ehgwb1huoahv112xqi5mk.zajbxwkqcjvnt1gunxntl"
          },
          "to": {
            "target": "obi41bninohy4snvlz1m7",
            "param": "pmofpdfv0a88ye7qhgc2f",
            "path": "obi41bninohy4snvlz1m7.pmofpdfv0a88ye7qhgc2f"
          }
        },
        {
          "id": "2awtp9lbdy66c670s25zo.aa",
          "from": {
            "target": "obi41bninohy4snvlz1m7",
            "param": "vb5yqy3isbba2ld8gjb5na",
            "path": "obi41bninohy4snvlz1m7.vb5yqy3isbba2ld8gjb5na"
          },
          "to": {
            "target": "n3mr51aig4mkncyt8lpbg",
            "param": "notA",
            "path": "n3mr51aig4mkncyt8lpbg.notA"
          }
        },
        {
          "id": "2awtp9lbdy66c670s25zo.ab",
          "from": {
            "target": "84wrbsrf22qanhqadwe978",
            "param": "isKeyDownOut",
            "path": "84wrbsrf22qanhqadwe978.isKeyDownOut"
          },
          "to": {
            "target": "2awtp9lbdy66c670s25zo",
            "param": "ab",
            "path": "2awtp9lbdy66c670s25zo.ab"
          }
        },
        {
          "id": "qf1hpzmnbhap3g58xo263b.select1",
          "from": {
            "target": "2awtp9lbdy66c670s25zo",
            "param": "ar",
            "path": "2awtp9lbdy66c670s25zo.ar"
          },
          "to": {
            "target": "qf1hpzmnbhap3g58xo263b",
            "param": "select1",
            "path": "qf1hpzmnbhap3g58xo263b.select1"
          }
        },
        {
          "id": "2awtp9lbdy66c670s25zo.aa",
          "from": {
            "target": "n3mr51aig4mkncyt8lpbg",
            "param": "notR",
            "path": "n3mr51aig4mkncyt8lpbg.notR"
          },
          "to": {
            "target": "2awtp9lbdy66c670s25zo",
            "param": "aa",
            "path": "2awtp9lbdy66c670s25zo.aa"
          }
        },
        {
          "id": "qf1hpzmnbhap3g58xo263b.select3",
          "from": {
            "target": "tmmlz7una1bbx6pvgacr9g",
            "param": "9mclho2pkelwm1p64zm5t",
            "path": "tmmlz7una1bbx6pvgacr9g.1ehgwb1huoahv112xqi5mk.9mclho2pkelwm1p64zm5t"
          },
          "to": {
            "target": "qf1hpzmnbhap3g58xo263b",
            "param": "select3",
            "path": "qf1hpzmnbhap3g58xo263b.select3"
          }
        },
        {
          "id": "tmmlz7una1bbx6pvgacr9g.zyr58ywgczoq3uduruanyq.9mclho2pkelwm1p64zm5t",
          "from": {
            "target": "qf1hpzmnbhap3g58xo263b",
            "param": "selectOut",
            "path": "qf1hpzmnbhap3g58xo263b.selectOut"
          },
          "to": {
            "target": "tmmlz7una1bbx6pvgacr9g",
            "param": "9mclho2pkelwm1p64zm5t",
            "path": "tmmlz7una1bbx6pvgacr9g.zyr58ywgczoq3uduruanyq.9mclho2pkelwm1p64zm5t"
          }
        }
      ],
      "values": {},
      "expandedParams": {
        "tmmlz7una1bbx6pvgacr9g.1ehgwb1huoahv112xqi5mk": true,
        "tmmlz7una1bbx6pvgacr9g.zyr58ywgczoq3uduruanyq": true
      }
    },
    "zdgq1qsxgh5f9dpdmv7a": {
      "id": "zdgq1qsxgh5f9dpdmv7a",
      "name": "isInAir",
      "core": false,
      "input": [
        {
          "id": "pmofpdfv0a88ye7qhgc2f",
          "name": "ypos",
          "type": "number"
        }
      ],
      "output": [
        {
          "id": "vb5yqy3isbba2ld8gjb5na",
          "name": "isInAir",
          "type": "boolean"
        }
      ],
      "tokens": [
        {
          "id": "xe49e89nv9jif64c8iflvk",
          "position": {
            "x": 630,
            "y": 34
          },
          "fn": "lessThan",
          "values": {
            "xe49e89nv9jif64c8iflvk.lb": 500
          },
          "expandedParams": {}
        }
      ],
      "wires": [
        {
          "id": "xe49e89nv9jif64c8iflvk.la",
          "from": {
            "target": "zdgq1qsxgh5f9dpdmv7a",
            "param": "pmofpdfv0a88ye7qhgc2f",
            "path": "zdgq1qsxgh5f9dpdmv7a.pmofpdfv0a88ye7qhgc2f"
          },
          "to": {
            "target": "xe49e89nv9jif64c8iflvk",
            "param": "la",
            "path": "xe49e89nv9jif64c8iflvk.la"
          }
        },
        {
          "id": "zdgq1qsxgh5f9dpdmv7a.vb5yqy3isbba2ld8gjb5na",
          "from": {
            "target": "xe49e89nv9jif64c8iflvk",
            "param": "lr",
            "path": "xe49e89nv9jif64c8iflvk.lr"
          },
          "to": {
            "target": "zdgq1qsxgh5f9dpdmv7a",
            "param": "vb5yqy3isbba2ld8gjb5na",
            "path": "zdgq1qsxgh5f9dpdmv7a.vb5yqy3isbba2ld8gjb5na"
          }
        }
      ],
      "values": {},
      "expandedParams": {}
    }
  },
  "mainFn": "urkjxr6zsnsiz9yizq7x8",
  "types": {
    "string": {
      "id": "string",
      "name": "string",
      "core": true,
      "defaultValue": ""
    },
    "number": {
      "id": "number",
      "name": "number",
      "core": true,
      "defaultValue": 0
    },
    "boolean": {
      "id": "boolean",
      "name": "boolean",
      "core": true,
      "defaultValue": false
    },
    "colour": {
      "id": "colour",
      "name": "colour",
      "core": true,
      "defaultValue": "#F00"
    },
    "imageSrc": {
      "id": "imageSrc",
      "name": "image source",
      "core": true,
      "defaultValue": "/sprites/Jump.png"
    },
    "through": {
      "id": "through",
      "name": "through",
      "core": true
    },
    "list": {
      "id": "list",
      "name": "list",
      "core": true,
      "defaultValue": []
    },
    "rect": {
      "id": "rect",
      "name": "rect",
      "params": [
        {
          "id": "x",
          "name": "x",
          "type": "number"
        },
        {
          "id": "y",
          "name": "y",
          "type": "number"
        },
        {
          "id": "height",
          "name": "height",
          "type": "number"
        },
        {
          "id": "width",
          "name": "width",
          "type": "number"
        },
        {
          "id": "colour",
          "name": "colour",
          "type": "colour"
        }
      ],
      "core": true
    },
    "text": {
      "id": "text",
      "name": "text",
      "params": [
        {
          "id": "x",
          "name": "x",
          "type": "number"
        },
        {
          "id": "y",
          "name": "y",
          "type": "number"
        },
        {
          "id": "text",
          "name": "text",
          "type": "string"
        },
        {
          "id": "colour",
          "name": "colour",
          "type": "colour"
        },
        {
          "id": "fontSize",
          "name": "font size",
          "type": "number"
        }
      ],
      "core": true
    },
    "image": {
      "id": "image",
      "name": "image",
      "params": [
        {
          "id": "x",
          "name": "x",
          "type": "number"
        },
        {
          "id": "y",
          "name": "y",
          "type": "number"
        },
        {
          "id": "height",
          "name": "height",
          "type": "number"
        },
        {
          "id": "width",
          "name": "width",
          "type": "number"
        },
        {
          "id": "imageSrc",
          "name": "image source",
          "type": "imageSrc"
        }
      ],
      "core": true
    },
    "scene": {
      "id": "scene",
      "name": "scene",
      "params": [
        {
          "id": "children",
          "name": "children",
          "type": "list"
        }
      ],
      "core": true
    },
    "input": {
      "id": "input",
      "name": "input",
      "params": [
        {
          "id": "keysDown",
          "name": "keysDown",
          "type": "list"
        }
      ],
      "core": true
    },
    "state": {
      "id": "state",
      "name": "state",
      "params": [
        {
          "id": "s9c1c1nbkeazla8wmx9fn",
          "name": "playerX",
          "type": "number"
        },
        {
          "id": "zajbxwkqcjvnt1gunxntl",
          "name": "playerY",
          "type": "number"
        },
        {
          "id": "9mclho2pkelwm1p64zm5t",
          "name": "playerYVel",
          "type": "number"
        },
        {
          "id": "q55wqw4o1ebe0ylkb71qmg",
          "name": "playerXVel",
          "type": "number"
        }
      ],
      "core": false
    },
    "7rbcmn20yrv4i47zf7geoa": {
      "id": "7rbcmn20yrv4i47zf7geoa",
      "name": "playerXvel",
      "params": [],
      "core": false
    },
    "r3zen2w53qgqk2gjyf30cg": {
      "id": "r3zen2w53qgqk2gjyf30cg",
      "name": "playerYvel",
      "params": [],
      "core": false
    }
  }
}
